{
  "learning_methods": [
    {
      "name": "费曼学习法",
      "description": "通过教授他人来加深理解的学习方法",
      "steps": [
        "选择一个概念",
        "尝试向他人解释这个概念",
        "发现理解中的漏洞",
        "重新学习并简化解释"
      ],
      "example": "学习机器学习中的梯度下降算法时，尝试向朋友解释这个算法的工作原理，发现自己在某些细节上理解不够深入，然后重新学习并简化解释"
    },
    {
      "name": "番茄工作法",
      "description": "通过时间管理提高学习效率的方法",
      "steps": [
        "设定25分钟的学习时间",
        "专注学习，不受干扰",
        "休息5分钟",
        "每4个番茄钟后休息15-30分钟"
      ],
      "example": "学习Python编程时，设置25分钟专注学习函数定义，然后休息5分钟，再继续学习下一个主题"
    },
    {
      "name": "主动回忆法",
      "description": "通过主动回忆而不是被动阅读来加强记忆",
      "steps": [
        "阅读学习材料",
        "合上书本，尝试回忆关键概念",
        "检查回忆的准确性",
        "重复这个过程"
      ],
      "example": "学习数据结构后，合上书本，尝试在白板上画出各种数据结构的图示并解释它们的特点"
    },
    {
      "name": "间隔重复法",
      "description": "在不同时间间隔重复学习以加强长期记忆",
      "steps": [
        "初次学习新知识",
        "在1天后复习",
        "在1周后再次复习",
        "在1个月后再次复习"
      ],
      "example": "学习算法复杂度分析后，按照1天、1周、1个月的时间间隔定期复习，确保长期记忆"
    }
  ],
  "recommendations": {
    "for_beginners": ["番茄工作法", "主动回忆法"],
    "for_intermediate": ["费曼学习法", "间隔重复法"],
    "for_advanced": ["费曼学习法", "项目实践法"]
  }
}